pyliveserver/__init__.py
pyliveserver/__main__.py
pyliveserver/server.py
pyliveserver-0.1.3.dist-info/LICENSE
pyliveserver-0.1.3.dist-info/METADATA
pyliveserver-0.1.3.dist-info/WHEEL
pyliveserver-0.1.3.dist-info/entry_points.txt
pyliveserver-0.1.3.dist-info/top_level.txt
pyliveserver-0.1.3.dist-info/RECORD
