Metadata-Version: 2.2
Name: pyliveserver
Version: 0.1.3
Summary: Un servidor local con recarga automática para desarrollo de sitios estáticos.
Home-page: https://github.com/javiscripto/pyliveserver
Author: Javier Manque (javiscripto)
Author-email: javier.manque.dev@gmail.com
Classifier: Development Status :: 3 - Alpha
Classifier: Intended Audience :: Developers
Classifier: Topic :: Software Development :: Build Tools
Classifier: License :: OSI Approved :: MIT License
Classifier: Programming Language :: Python :: 3
License-File: LICENSE
Requires-Dist: livereload
Dynamic: author
Dynamic: author-email
Dynamic: classifier
Dynamic: description
Dynamic: description-content-type
Dynamic: home-page
Dynamic: requires-dist
Dynamic: summary
